odoo/addons/l10n_nl_xaf_auditfile_export/README.rst
odoo/addons/l10n_nl_xaf_auditfile_export/__init__.py
odoo/addons/l10n_nl_xaf_auditfile_export/__manifest__.py
odoo/addons/l10n_nl_xaf_auditfile_export/data/XmlAuditfileFinancieel3.2.xsd
odoo/addons/l10n_nl_xaf_auditfile_export/i18n/l10n_nl_xaf_auditfile_export.pot
odoo/addons/l10n_nl_xaf_auditfile_export/i18n/nl.po
odoo/addons/l10n_nl_xaf_auditfile_export/models/__init__.py
odoo/addons/l10n_nl_xaf_auditfile_export/models/ir_qweb.py
odoo/addons/l10n_nl_xaf_auditfile_export/models/xaf_auditfile_export.py
odoo/addons/l10n_nl_xaf_auditfile_export/readme/CONFIGURE.rst
odoo/addons/l10n_nl_xaf_auditfile_export/readme/CONTRIBUTORS.rst
odoo/addons/l10n_nl_xaf_auditfile_export/readme/CREDITS.rst
odoo/addons/l10n_nl_xaf_auditfile_export/readme/DESCRIPTION.rst
odoo/addons/l10n_nl_xaf_auditfile_export/readme/ROADMAP.rst
odoo/addons/l10n_nl_xaf_auditfile_export/readme/USAGE.rst
odoo/addons/l10n_nl_xaf_auditfile_export/security/ir.model.access.csv
odoo/addons/l10n_nl_xaf_auditfile_export/security/ir_rule.xml
odoo/addons/l10n_nl_xaf_auditfile_export/static/description/icon.png
odoo/addons/l10n_nl_xaf_auditfile_export/static/description/index.html
odoo/addons/l10n_nl_xaf_auditfile_export/tests/__init__.py
odoo/addons/l10n_nl_xaf_auditfile_export/tests/test_l10n_nl_xaf_auditfile_export.py
odoo/addons/l10n_nl_xaf_auditfile_export/views/menu.xml
odoo/addons/l10n_nl_xaf_auditfile_export/views/templates.xml
odoo/addons/l10n_nl_xaf_auditfile_export/views/xaf_auditfile_export.xml
odoo14_addon_l10n_nl_xaf_auditfile_export-14.0.3.2.1.dist-info/METADATA
odoo14_addon_l10n_nl_xaf_auditfile_export-14.0.3.2.1.dist-info/WHEEL
odoo14_addon_l10n_nl_xaf_auditfile_export-14.0.3.2.1.dist-info/top_level.txt
odoo14_addon_l10n_nl_xaf_auditfile_export-14.0.3.2.1.dist-info/RECORD
